float_adder.vhd
library IEEE;
use IEEE.std_logic_1164.all;
use IEEE.numeric_std.all;
use work.utils.all;

entity float_adder is
    generic (
        NE : natural := 8;
        NF : natural := 23);
    port (
        x_i : in std_logic_vector((NE + NF) downto 0);
        y_i : in std_logic_vector((NE + NF) downto 0);
        res_o : out std_logic_vector((NE + NF) downto 0)
    );
end float_adder;

architecture float_adder_arch of float_adder is

    --Bits de signo de cada uno de los registros
    signal sa : std_logic; --Bit signo del número mayor
    signal sb : std_logic; --Bit signo de número menor 
    signal sp : std_logic; --Bit signo parcial
    signal sr : std_logic; --Bit signo resultante

    --Bits de exponente de cada uno de los registros
    signal ea : unsigned(NE - 1 downto 0) := (others => '0'); --Exponente del número mayor
    signal eb : unsigned(NE - 1 downto 0) := (others => '0'); --Exponente del número menor
    signal ep : integer := 0; --Exponente parcial (tiene 1 bit más para verificar saturación) 
    signal er : unsigned(NE - 1 downto 0) := (others => '0'); --Exponente resultante si no  hay saturación
    signal edif: integer := 0; --Diferencia entre el exponente mayor y el menor
    signal esat : unsigned(NE - 1 downto 0) := (others => '0'); --Exponente resultante si hay saturación
    constant ezero : unsigned(NE - 1 downto 0) := (others => '0'); --Constante usada cuando resultado es cero

    --Bits de mantisa de cada uno de los registros
    signal ma : unsigned(NF - 1 downto 0) := (others => '0'); --Mantisa del número mayor
    signal mb : unsigned(NF - 1 downto 0) := (others => '0'); --Mantisa del número menor
    signal mp : unsigned(NF - 1 downto 0) := (others => '0'); --Mantisa resultante cuando no hay saturación
    constant msat : unsigned(NF - 1 downto 0) := (others => '1'); --Usada cuando hay saturación
    constant mzero : unsigned(NF - 1 downto 0) := (others => '0'); --Usada cuando resultado es cero
    signal mr : unsigned(NF - 1 downto 0) := (others => '0'); --Mantisa resultante
 
    --Auxiliares
    signal aligna: unsigned(NF + 1 downto 0) := (others => '0'); --Alineación del mayor (solo se concatena '1') 
    signal alignb: unsigned(NF + 1 downto 0) := (others => '0'); --Alineación del menor
    signal sum: unsigned(NF + 1 downto 0) := (others => '0'); --Resultado de la suma/resta (sin signo)
    signal sum_shifted: unsigned(NF + 1 downto 0) := (others => '0'); --Resultado de la suma/resta shifteada hasta primer '1'
    signal lead: integer := 0; --Cantidad de ceros que hay hasta el primer '1' de suma de mantisas alineadas
    signal sat: std_logic := '0';

begin
    --Inicialización exponente saturación
    esat(NE - 1 downto 1) <= (others => '1');
    esat(0) <= '0';

    --Se asigna el menor a "b" a y el mayor a "a":
    P_SEL_MENOR_MAYOR : process (x_i, y_i)
        variable sx : std_logic; --Bit signo de x_i
        variable sy : std_logic; --Bit signo de y_i
        variable ex : unsigned(NE - 1 downto 0); --Exponente de x_i
        variable ey : unsigned(NE - 1 downto 0); --Exponente de y_i
        variable mx : unsigned(NF - 1 downto 0); --Mantisa de cada una de x_i
        variable my : unsigned(NF - 1 downto 0); --Mantisa de cada una de y_i

    begin
        sx := x_i(NF + NE);
        sy := y_i(NF + NE);
        ex := unsigned(x_i((NE + NF) - 1 downto NF));
        ey := unsigned(y_i((NE + NF) - 1 downto NF));
        mx := unsigned(x_i(NF - 1 downto 0));
        my := unsigned(y_i(NF - 1 downto 0));

        if (ex & mx) > (ey & my) then
            sa <= sx;
            ea <= ex;
            ma <= mx;
            sb <= sy;
            eb <= ey;
            mb <= my;
        else
            sa <= sy;
            ea <= ey;
            ma <= my;
            sb <= sx;
            eb <= ex;
            mb <= mx;
        end if;
    end process;

    --Se alinean los números:
    edif <= to_integer(ea - eb);
    aligna(NF downto 0) <= '1' & ma; --Mantisa mayor alineada con 1 explícito
    alignb(NF downto 0) <= (('1' & mb) srl edif) when (edif <= NF) else (others => '0'); --Mantisa menor alineada con 1 explícito

    --Se realiza la suma/resta:
    sum <= (aligna + alignb) when (sa = sb) else (aligna - alignb);
    sp <= sa; --El signo del número resultante siempre va a ser igual al del mayor

    --Se obtiene el exponente y mantisas parciales:
    lead <= get_lead(sum(NF downto 0));  --Si hubo carry out lead <= -1
    ep <= to_integer(ea) + 1 when sum(NF+1) = '1' else to_integer(ea) - lead; --Desplazamiento del exponente
    --Se hace desplazamientos de suma dependiendo de los dos primeros bits de sum 
    sum_shifted <= sum when sum(NF+1 downto NF) = "11" else 
                    sum srl 1 when sum(NF+1 downto NF) = "10" else 
                    sum sll lead;
    mp <= sum_shifted((NF - 1) downto 0); --Mantisa parcial, -1 en el rango para sacar el 1 implícito

    --Verificación de saturación y obtención de valores resultantes
    sr <= sp;
    er <= ezero when (ep < 0) else esat when (ep > 254) else to_unsigned(ep, NE);
    mr <= mzero when (ep < 0) else msat when (ep > 254) else mp;
    sat <= '1' when (ep < 0 or ep > 254) else '0';
    
    --Salida final
    res_o <= (std_logic_vector(sr & er & mr));

end float_adder_arch;

float_adder_tb.vhd
library IEEE;
use IEEE.std_logic_1164.all;
use IEEE.numeric_std.all;
use std.textio.all;

entity float_adder_tb is
end entity float_adder_tb;

architecture float_adder_tb_arch of float_adder_tb is

    constant FILE_PATH  : string := "test_sum_float_23_6.txt";
    constant TCK        : time := 20 ns; -- Periodo de reloj
    constant F_SIZE     : natural := 16; -- Tamaño de mantisa
    constant EXP_SIZE   : natural := 6;  -- Tamaño del exponente
    constant WORD_SIZE  : natural := EXP_SIZE + F_SIZE + 1; -- Tamaño de datos
   

    signal clk          : std_logic := '0';
    signal add_sub_tb   : std_logic := '0';
    signal x_file       : std_logic_vector(WORD_SIZE-1 downto 0) := (others => '0');
    signal y_file       : std_logic_vector(WORD_SIZE-1 downto 0) := (others => '0');
    signal z_file       : std_logic_vector(WORD_SIZE-1 downto 0) := (others => '0');
    signal z_dut        : std_logic_vector(WORD_SIZE-1 downto 0) := (others => '0');

    signal ciclos   : integer := 0;
    signal errores  : integer := 0;

    file datos : text open read_mode is FILE_PATH;
    
begin

    clk <= not(clk) after TCK/2; -- Reloj

    Test_Sequence: process 
        variable l   : line;
        variable ch  : character := ' ';
        variable aux : integer;
    begin
        while not(endfile(datos)) loop
            wait until rising_edge(clk);
            -- Solo para debugging
            ciclos <= ciclos + 1;
            -- Se lee una linea del archivo de valores de prueba
            readline(datos, l);
            -- Se extrae un entero de la linea
            read(l, aux);
            -- Se carga el valor del operando X
            x_file <= std_logic_vector(to_unsigned(aux, WORD_SIZE));
            -- Se lee un caracter (el espacio)
            read(l, ch);
            -- Se lee otro entero de la linea
            read(l, aux);
            -- Se carga el valor del operando Y
            y_file <= std_logic_vector(to_unsigned(aux, WORD_SIZE));
            -- Se lee otro caracter (el espacio)
            read(l, ch);
            -- Se lee otro entero
            read(l, aux);
            -- Se carga el valor de la salida (resultado)
            z_file <= std_logic_vector(to_unsigned(aux, WORD_SIZE));
        end loop;
    
        file_close(datos); -- Se cierra el archivo

        
        -- Se aborta la simulacion (fin del archivo)
        assert false report
            "Fin de la simulacion" severity failure;

    end process Test_Sequence;

    -- Instanciacion del DUT
    DUT: entity work.float_adder
    generic map(
        NF => F_SIZE,
        NE => EXP_SIZE
    )
    port map(
        x_i       => x_file,
        y_i       => y_file,
        res_o       => z_dut
    );


    verificacion: process(clk)
    begin
        if rising_edge(clk) then
            assert to_integer(unsigned(z_file)) = to_integer(unsigned(z_dut)) report
                "Error: Salida del DUT no coincide con referencia (salida del DUT = " &
                integer'image(to_integer(unsigned(z_dut))) &
                ", salida del archivo = " &
                integer'image(to_integer(unsigned(z_file))) & ")"
                severity warning;
            
            if to_integer(unsigned(z_file)) /= to_integer(unsigned(z_dut)) then
                errores <= errores + 1;
            end if;
        end if;
    end process;

end architecture float_adder_tb_arch;

float_adder_tb.vcd
$date
  Sat Nov 11 21:39:26 2023
$end
$version
  GHDL v0
$end
$timescale
  1 fs
$end
$scope module standard $end
$upscope $end
$scope module std_logic_1164 $end
$upscope $end
$scope module numeric_std $end
$upscope $end
$scope module textio $end
$upscope $end
$scope module utils $end
$upscope $end
$scope module float_adder_tb $end
$var reg 1 ! clk $end
$var reg 1 " add_sub_tb $end
$var reg 23 # x_file[22:0] $end
$var reg 23 $ y_file[22:0] $end
$var reg 23 % z_file[22:0] $end
$var reg 23 & z_dut[22:0] $end
$var integer 32 ' ciclos $end
$var integer 32 ( errores $end
$scope module dut $end
$var reg 23 ) x_i[22:0] $end
$var reg 23 * y_i[22:0] $end
$var reg 23 + res_o[22:0] $end
$var reg 1 , sa $end
$var reg 1 - sb $end
$var reg 1 . sp $end
$var reg 1 / sr $end
$var reg 6 0 ea[5:0] $end
$var reg 6 1 eb[5:0] $end
$var integer 32 2 ep $end
$var reg 6 3 er[5:0] $end
$var integer 32 4 edif $end
$var reg 6 5 esat[5:0] $end
$var reg 16 6 ma[15:0] $end
$var reg 16 7 mb[15:0] $end
$var reg 16 8 mp[15:0] $end
$var reg 16 9 mr[15:0] $end
$var reg 18 : aligna[17:0] $end
$var reg 18 ; alignb[17:0] $end
$var reg 18 < sum[17:0] $end
$var reg 18 = sum_shifted[17:0] $end
$var integer 32 > lead $end
$var reg 1 ? sat $end
$upscope $end
$upscope $end
$enddefinitions $end
#0
0!
0"
b00000000000000000000000 #
b00000000000000000000000 $
b00000000000000000000000 %
b00000010000000000000000 &
b0 '
b0 (
b00000000000000000000000 )
b00000000000000000000000 *
b00000010000000000000000 +
0,
0-
0.
0/
b000000 0
b000000 1
b1 2
b000001 3
b0 4
b111110 5
b0000000000000000 6
b0000000000000000 7
b0000000000000000 8
b0000000000000000 9
b010000000000000000 :
b010000000000000000 ;
b100000000000000000 <
b010000000000000000 =
b10000 >
0?
#10000000
1!
b10110111100110100100100 #
b10111100001000000001001 $
b10111100100100110101101 %
b10111100100100110101101 &
b1 '
b1 (
b10110111100110100100100 )
b10111100001000000001001 *
b10111100100100110101101 +
1,
1-
1.
1/
b011110 0
b011011 1
b11110 2
b011110 3
b11 4
b0001000000001001 6
b1100110100100100 7
b0100100110101101 8
b0100100110101101 9
b010001000000001001 :
b000011100110100100 ;
b010100100110101101 <
b010100100110101101 =
b0 >
#20000000
0!
#30000000
1!
b10111100011001001100111 #
b10111001101100011011011 $
b10111101010100010011101 %
b10111101010100010011101 &
b10 '
b10111100011001001100111 )
b10111001101100011011011 *
b10111101010100010011101 +
b011100 1
b10 4
b0011001001100111 6
b1101100011011011 7
b1010100010011101 8
b1010100010011101 9
b010011001001100111 :
b000111011000110110 ;
b011010100010011101 <
b011010100010011101 =
#40000000
0!
#50000000
1!
b00111000011110110110111 #
b00111100101000111111000 $
b00111101010000101100101 %
b00111101010000101100101 &
b11 '
b00111000011110110110111 )
b00111100101000111111000 *
b00111101010000101100101 +
0,
0-
0.
0/
b0101000111111000 6
b0011110110110111 7
b1010000101100101 8
b1010000101100101 9
b010101000111111000 :
b000100111101101101 ;
b011010000101100101 <
b011010000101100101 =
#60000000
0!
#70000000
1!
b00111001100011001111011 #
b10111010100010110010001 $
b10110111000100101001110 %
b10110111000100101010000 &
b100 '
b00111001100011001111011 )
b10111010100010110010001 *
b10110111000100101010000 +
1,
1.
1/
b011101 0
b11011 2
b011011 3
b1 4
b0100010110010001 6
b1100011001111011 7
b1000100101010000 8
b1000100101010000 9
b010100010110010001 :
b001110001100111101 ;
b000110001001010100 <
b011000100101010000 =
b10 >
#80000000
0!
#90000000
1!
b10110110111110000111100 #
b10110111100101000111001 $
b10111001010001100111010 %
b10111000100011001110101 &
b101 '
b10 (
b10110110111110000111100 )
b10110111100101000111001 *
b10111000100011001110101 +
1-
b011011 0
b011011 1
b11100 2
b011100 3
b0 4
b1100101000111001 6
b0111110000111100 7
b0100011001110101 8
b0100011001110101 9
b011100101000111001 :
b010111110000111100 ;
b110100011001110101 <
b110100011001110101 =
b0 >
#100000000
0!
#110000000
1!
b10111000111110000001100 #
b10111011010010100010100 $
b10111100011000110001101 %
b10111100011000110001101 &
b110 '
b11 (
b10111000111110000001100 )
b10111011010010100010100 *
b10111100011000110001101 +
b011101 0
b011100 1
b11110 2
b011110 3
b1 4
b1010010100010100 6
b0111110000001100 7
b0011000110001101 8
b0011000110001101 9
b011010010100010100 :
b001011111000000110 ;
b100110001100011010 <
b010011000110001101 =
b10 >
#120000000
0!
#130000000
1!
b10111011000110100111101 #
b00110000110011101100100 $
b10111011000001000000001 %
b10111011000001000000010 &
b111 '
b10111011000110100111101 )
b00110000110011101100100 *
b10111011000001000000010 +
0-
b011000 1
b11101 2
b011101 3
b101 4
b1000110100111101 6
b0110011101100100 7
b1000001000000010 8
b1000001000000010 9
b011000110100111101 :
b000000101100111011 ;
b011000001000000010 <
b011000001000000010 =
b0 >
#140000000
0!
#150000000
1!
b00111101110100011100000 #
b00110111101001001101100 $
b00111110001000110010110 %
b00111110001000110010110 &
b1000 '
b100 (
b00111101110100011100000 )
b00110111101001001101100 *
b00111110001000110010110 +
0,
0.
0/
b011110 0
b011011 1
b11111 2
b011111 3
b11 4
b1110100011100000 6
b1101001001101100 7
b0001000110010110 8
b0001000110010110 9
b011110100011100000 :
b000011101001001101 ;
b100010001100101101 <
b010001000110010110 =
b11 >
#160000000
0!
#170000000
1!
b00111100000010010001101 #
b00111010100001011110001 $
b00111101010011000000101 %
b00111101010011000000101 &
b1001 '
b00111100000010010001101 )
b00111010100001011110001 *
b00111101010011000000101 +
b011101 1
b11110 2
b011110 3
b1 4
b0000010010001101 6
b0100001011110001 7
b1010011000000101 8
b1010011000000101 9
b010000010010001101 :
b001010000101111000 ;
b011010011000000101 <
b011010011000000101 =
b0 >
#180000000
0!
#190000000
1!
b00110011110111101001011 #
b00111001010100001111010 $
b00111001110011001100011 %
b00111001110011001100011 &
b1010 '
b00110011110111101001011 )
b00111001010100001111010 *
b00111001110011001100011 +
b011100 0
b011001 1
b11100 2
b011100 3
b11 4
b1010100001111010 6
b1110111101001011 7
b1110011001100011 8
b1110011001100011 9
b011010100001111010 :
b000011110111101001 ;
b011110011001100011 <
b011110011001100011 =
b0 >
#200000000
0!
#210000000
1!
b10101110100000010100000 #
b00111011010010000011000 $
b00111011001111100010101 %
b00111011001111100010110 &
b1011 '
b10101110100000010100000 )
b00111011010010000011000 *
b00111011001111100010110 +
1-
b011101 0
b010111 1
b11101 2
b011101 3
b110 4
b1010010000011000 6
b0100000010100000 7
b1001111100010110 8
b1001111100010110 9
b011010010000011000 :
b000000010100000010 ;
b011001111100010110 <
b011001111100010110 =
#220000000
0!
#230000000
1!
b10111011010110111011100 #
b00111011011100000100100 $
b00110000100100100000000 %
b00110000100100100000000 &
b1100 '
b101 (
b10111011010110111011100 )
b00111011011100000100100 *
b00110000100100100000000 +
b011101 1
b11000 2
b011000 3
b0 4
b1011100000100100 6
b1010110111011100 7
b0100100100000000 8
b0100100100000000 9
b011011100000100100 :
b011010110111011100 ;
b000000101001001000 <
b010100100100000000 =
b101 >
#240000000
0!
#250000000
1!
b10111000100100110000010 #
b00111001111000001011110 $
b00110110100110110111000 %
b00110110100110110111000 &
b1101 '
b10111000100100110000010 )
b00111001111000001011110 *
b00110110100110110111000 +
b011100 0
b011100 1
b11011 2
b011011 3
b1111000001011110 6
b0100100110000010 7
b0100110110111000 8
b0100110110111000 9
b011111000001011110 :
b010100100110000010 ;
b001010011011011100 <
b010100110110111000 =
b1 >
#260000000
0!
#270000000
1!
b10111010011110100101110 #
b00110011110111101001111 $
b10111010001111000111001 %
b10111010001111000111010 &
b1110 '
b10111010011110100101110 )
b00110011110111101001111 *
b10111010001111000111010 +
1,
0-
1.
1/
b011101 0
b011001 1
b11101 2
b011101 3
b100 4
b0011110100101110 6
b1110111101001111 7
b0001111000111010 8
b0001111000111010 9
b010011110100101110 :
b000001111011110100 ;
b010001111000111010 <
b010001111000111010 =
b0 >
#280000000
0!
#290000000
1!
b10111011010111101101010 #
b00111001001000000101010 $
b10111001100111010101010 %
b10111001100111010101010 &
b1111 '
b110 (
b10111011010111101101010 )
b00111001001000000101010 *
b10111001100111010101010 +
b011100 1
b11100 2
b011100 3
b1 4
b1010111101101010 6
b1001000000101010 7
b1100111010101010 8
b1100111010101010 9
b011010111101101010 :
b001100100000010101 ;
b001110011101010101 <
b011100111010101010 =
b1 >
#300000000
0!
#310000000
1!
b00111001110110100100011 #
b10111001100010111111011 $
b00110010011100101000000 %
b00110010011100101000000 &
b10000 '
b00111001110110100100011 )
b10111001100010111111011 *
b00110010011100101000000 +
0,
1-
0.
0/
b011100 0
b11001 2
b011001 3
b0 4
b1110110100100011 6
b1100010111111011 7
b0011100101000000 8
b0011100101000000 9
b011110110100100011 :
b011100010111111011 ;
b000010011100101000 <
b010011100101000000 =
b11 >
#320000000
0!
#330000000
1!
b00111001011100111011101 #
b10111010101100100010111 $
b10110111111000010100010 %
b10110111111000010100100 &
b10001 '
b00111001011100111011101 )
b10111010101100100010111 *
b10110111111000010100100 +
1,
0-
1.
1/
b011101 0
b11011 2
b011011 3
b1 4
b0101100100010111 6
b1011100111011101 7
b1111000010100100 8
b1111000010100100 9
b010101100100010111 :
b001101110011101110 ;
b000111110000101001 <
b011111000010100100 =
b10 >
#340000000
0!
#350000000
1!
b10110110111111101010100 #
b00111001101000111000010 $
b00111000001001000011000 %
b00111000001001000011000 &
b10010 '
b111 (
b10110110111111101010100 )
b00111001101000111000010 *
b00111000001001000011000 +
0,
1-
0.
0/
b011100 0
b011011 1
b11100 2
b011100 3
b1101000111000010 6
b0111111101010100 7
b0001001000011000 8
b0001001000011000 9
b011101000111000010 :
b001011111110101010 ;
b010001001000011000 <
b010001001000011000 =
b0 >
#360000000
0!
#370000000
1!
b10111000101001110110100 #
b00111011001110110001010 $
b00111001110011101100000 %
b00111001110011101100000 &
b10011 '
b10111000101001110110100 )
b00111011001110110001010 *
b00111001110011101100000 +
b011101 0
b011100 1
b11100 2
b011100 3
b1001110110001010 6
b0101001110110100 7
b1110011101100000 8
b1110011101100000 9
b011001110110001010 :
b001010100111011010 ;
b001111001110110000 <
b011110011101100000 =
b1 >
#380000000
0!
#390000000
1!
b10111000001000001010000 #
b00111010100010001101101 $
b00111000111100010001010 %
b00111000111100010001010 &
b10100 '
b10111000001000001010000 )
b00111010100010001101101 *
b00111000111100010001010 +
b0100010001101101 6
b0001000001010000 7
b0111100010001010 8
b0111100010001010 9
b010100010001101101 :
b001000100000101000 ;
b001011110001000101 <
b010111100010001010 =
#400000000
0!
#410000000
1!
b10111001010010110010001 #
b00110100000110100110001 $
b10111000110001001000100 %
b10111000110001001000101 &
b10101 '
b10111001010010110010001 )
b00110100000110100110001 *
b10111000110001001000101 +
1,
0-
1.
1/
b011100 0
b011010 1
b11100 2
b011100 3
b10 4
b1010010110010001 6
b0000110100110001 7
b0110001001000101 8
b0110001001000101 9
b011010010110010001 :
b000100001101001100 ;
b010110001001000101 <
b010110001001000101 =
b0 >
#420000000
0!
#430000000
1!
b00110110001000101010000 #
b10111011011101101111111 $
b10111010111011100101011 %
b10111010111011100101011 &
b10110 '
b1000 (
b00110110001000101010000 )
b10111011011101101111111 *
b10111010111011100101011 +
b011101 0
b011011 1
b11101 2
b011101 3
b1011101101111111 6
b0001000101010000 7
b0111011100101011 8
b0111011100101011 9
b011011101101111111 :
b000100010001010100 ;
b010111011100101011 <
b010111011100101011 =
#440000000
0!
#450000000
1!
b00111010010110001101100 #
b00110100101100111111110 $
b00111010101011110101011 %
b00111010101011110101011 &
b10111 '
b00111010010110001101100 )
b00110100101100111111110 *
b00111010101011110101011 +
0,
0.
0/
b011010 1
b11 4
b0010110001101100 6
b0101100111111110 7
b0101011110101011 8
b0101011110101011 9
b010010110001101100 :
b000010101100111111 ;
b010101011110101011 <
b010101011110101011 =
#460000000
0!
#470000000
1!
b10110101010000011010111 #
b00111000101000100010101 $
b00110111101000110111110 %
b00110111101000111000000 &
b11000 '
b10110101010000011010111 )
b00111000101000100010101 *
b00110111101000111000000 +
1-
b011100 0
b11011 2
b011011 3
b10 4
b0101000100010101 6
b1010000011010111 7
b1101000111000000 8
b1101000111000000 9
b010101000100010101 :
b000110100000110101 ;
b001110100011100000 <
b011101000111000000 =
b1 >
#480000000
0!
#490000000
1!
b00110110000111101101111 #
b10111000110101001010111 $
b10110111100010100111111 %
b10110111100010101000000 &
b11001 '
b1001 (
b00110110000111101101111 )
b10111000110101001010111 *
b10110111100010101000000 +
1,
0-
1.
1/
b011011 1
b11011 2
b011011 3
b1 4
b0110101001010111 6
b0000111101101111 7
b1100010101000000 8
b1100010101000000 9
b010110101001010111 :
b001000011110110111 ;
b001110001010100000 <
b011100010101000000 =
b1 >
#500000000
0!
#510000000
1!
b10110110100010101111100 #
b00111011011110111110101 $
b00111010110110010010110 %
b00111010110110010010110 &
b11010 '
b1010 (
b10110110100010101111100 )
b00111011011110111110101 *
b00111010110110010010110 +
0,
1-
0.
0/
b011101 0
b11101 2
b011101 3
b10 4
b1011110111110101 6
b0100010101111100 7
b0110110010010110 8
b0110110010010110 9
b011011110111110101 :
b000101000101011111 ;
b010110110010010110 <
b010110110010010110 =
b0 >
#520000000
0!
#530000000
1!
b00110100001010011100101 #
b10111100000110001011010 $
b10111011111011000010111 %
b10111011111011000011000 &
b11011 '
b00110100001010011100101 )
b10111100000110001011010 *
b10111011111011000011000 +
1,
0-
1.
1/
b011110 0
b011010 1
b11101 2
b011101 3
b100 4
b0000110001011010 6
b0001010011100101 7
b1111011000011000 8
b1111011000011000 9
b010000110001011010 :
b000001000101001110 ;
b001111101100001100 <
b011111011000011000 =
b1 >
#540000000
0!
#550000000
1!
b10110011101010011010100 #
b10110101011111011011010 $
b10110110101010010100010 %
b10110110101010010100010 &
b11100 '
b1011 (
b10110011101010011010100 )
b10110101011111011011010 *
b10110110101010010100010 +
1-
b011010 0
b011001 1
b11011 2
b011011 3
b1 4
b1011111011011010 6
b1101010011010100 7
b0101010010100010 8
b0101010010100010 9
b011011111011011010 :
b001110101001101010 ;
b101010100101000100 <
b010101010010100010 =
b1 >
#560000000
0!
#570000000
1!
b00111011110110001001100 #
b10111001111010010100011 $
b00111001110001111110101 %
b00111001110001111110110 &
b11101 '
b00111011110110001001100 )
b10111001111010010100011 *
b00111001110001111110110 +
0,
0.
0/
b011101 0
b011100 1
b11100 2
b011100 3
b1110110001001100 6
b1111010010100011 7
b1110001111110110 8
b1110001111110110 9
b011110110001001100 :
b001111101001010001 ;
b001111000111111011 <
b011110001111110110 =
#580000000
0!
#590000000
1!
b10110110101011100101010 #
b00110110100101100000001 $
b10101101000010100100000 %
b10101101000010100100000 &
b11110 '
b1100 (
b10110110101011100101010 )
b00110110100101100000001 *
b10101101000010100100000 +
1,
0-
1.
1/
b011011 0
b011011 1
b10110 2
b010110 3
b0 4
b0101011100101010 6
b0100101100000001 7
b1000010100100000 8
b1000010100100000 9
b010101011100101010 :
b010100101100000001 ;
b000000110000101001 <
b011000010100100000 =
b101 >
#600000000
0!
#610000000
1!
b10110010011100011001011 #
b10111110010011000100001 $
b10111110010101100000100 %
b10111110010101100000100 &
b11111 '
b10110010011100011001011 )
b10111110010011000100001 *
b10111110010101100000100 +
1-
b011111 0
b011001 1
b11111 2
b011111 3
b110 4
b0010011000100001 6
b0011100011001011 7
b0010101100000100 8
b0010101100000100 9
b010010011000100001 :
b000000010011100011 ;
b010010101100000100 <
b010010101100000100 =
b0 >
#620000000
0!
#630000000
1!
b00110001011100111001111 #
b00111010101000100100111 $
b00111010101111011110101 %
b00111010101111011110101 &
b100000 '
b00110001011100111001111 )
b00111010101000100100111 *
b00111010101111011110101 +
0,
0-
0.
0/
b011101 0
b011000 1
b11101 2
b011101 3
b101 4
b0101000100100111 6
b1011100111001111 7
b0101111011110101 8
b0101111011110101 9
b010101000100100111 :
b000000110111001110 ;
b010101111011110101 <
b010101111011110101 =
#640000000
0!
#650000000
1!
b10111000110111011010101 #
b10111000001101001110001 $
b10111010100010010100011 %
b10111010100010010100011 &
b100001 '
b10111000110111011010101 )
b10111000001101001110001 *
b10111010100010010100011 +
1,
1-
1.
1/
b011100 0
b011100 1
b11101 2
b011101 3
b0 4
b0110111011010101 6
b0001101001110001 7
b0100010010100011 8
b0100010010100011 9
b010110111011010101 :
b010001101001110001 ;
b101000100101000110 <
b010100010010100011 =
b1 >
#660000000
0!
#670000000
1!
b10111011000011111111001 #
b00111101110000001101000 $
b00111100001110001101011 %
b00111100001110001101100 &
b100010 '
b10111011000011111111001 )
b00111101110000001101000 *
b00111100001110001101100 +
0,
0.
0/
b011110 0
b011101 1
b11110 2
b011110 3
b1 4
b1110000001101000 6
b1000011111111001 7
b0001110001101100 8
b0001110001101100 9
b011110000001101000 :
b001100001111111100 ;
b010001110001101100 <
b010001110001101100 =
b0 >
#680000000
0!
#690000000
1!
b10111100011111000000101 #
b10111100011101111111100 $
b10111110011110100000000 %
b10111110011110100000000 &
b100011 '
b1101 (
b10111100011111000000101 )
b10111100011101111111100 *
b10111110011110100000000 +
1,
1.
1/
b011110 1
b11111 2
b011111 3
b0 4
b0011111000000101 6
b0011101111111100 7
b0011110100000000 8
b0011110100000000 9
b010011111000000101 :
b010011101111111100 ;
b100111101000000001 <
b010011110100000000 =
b10 >
#700000000
0!
#710000000
1!
b10111010111010000010100 #
b00111011111010100100010 $
b00111000000001000011100 %
b00111000000001000011100 &
b100100 '
b10111010111010000010100 )
b00111011111010100100010 *
b00111000000001000011100 +
0,
0.
0/
b011101 0
b011101 1
b11100 2
b011100 3
b1111010100100010 6
b0111010000010100 7
b0000001000011100 8
b0000001000011100 9
b011111010100100010 :
b010111010000010100 ;
b001000000100001110 <
b010000001000011100 =
b1 >
#720000000
0!
#730000000
1!
b00110110000001100000000 #
b00110111000111110001101 $
b00111000100100101000110 %
b00111000100100101000110 &
b100101 '
b00110110000001100000000 )
b00110111000111110001101 *
b00111000100100101000110 +
0-
b011011 0
b011011 1
b11100 2
b011100 3
b1000111110001101 6
b0000001100000000 7
b0100100101000110 8
b0100100101000110 9
b011000111110001101 :
b010000001100000000 ;
b101001001010001101 <
b010100100101000110 =
b1 >
#740000000
0!
#750000000
1!
b00111000000010010111011 #
b00111001000101101111101 $
b00111010100100000011100 %
b00111010100100000011100 &
b100110 '
b00111000000010010111011 )
b00111001000101101111101 *
b00111010100100000011100 +
b011100 0
b011100 1
b11101 2
b011101 3
b1000101101111101 6
b0000010010111011 7
b0100100000011100 8
b0100100000011100 9
b011000101101111101 :
b010000010010111011 ;
b101001000000111000 <
b010100100000011100 =
#760000000
0!
#770000000
1!
b10111000110001011000111 #
b10110111100101101011110 $
b10111010010010000111011 %
b10111010010010000111011 &
b100111 '
b10111000110001011000111 )
b10110111100101101011110 *
b10111010010010000111011 +
1,
1-
1.
1/
b011011 1
b1 4
b0110001011000111 6
b1100101101011110 7
b0010010000111011 8
b0010010000111011 9
b010110001011000111 :
b001110010110101111 ;
b100100100001110110 <
b010010010000111011 =
b10 >
#780000000
0!
#790000000
1!
b10110100100111000001000 #
b00111010000011000001111 $
b00111001011100010011100 %
b00111001011100010011100 &
b101000 '
b10110100100111000001000 )
b00111010000011000001111 *
b00111001011100010011100 +
0,
0.
0/
b011101 0
b011010 1
b11100 2
b011100 3
b11 4
b0000011000001111 6
b0100111000001000 7
b1011100010011100 8
b1011100010011100 9
b010000011000001111 :
b000010100111000001 ;
b001101110001001110 <
b011011100010011100 =
b1 >
#800000000
0!
#810000000
1!
b00111101010111000111110 #
b10110111101010111111010 $
b00111100111001101111110 %
b00111100111001101111111 &
b101001 '
b00111101010111000111110 )
b10110111101010111111010 *
b00111100111001101111111 +
b011110 0
b011011 1
b11110 2
b011110 3
b1010111000111110 6
b1101010111111010 7
b0111001101111111 8
b0111001101111111 9
b011010111000111110 :
b000011101010111111 ;
b010111001101111111 <
b010111001101111111 =
b0 >
#820000000
0!
#830000000
1!
b00111010000110100100101 #
b00111000011100000011011 $
b00111011010100100110010 %
b00111011010100100110010 &
b101010 '
b1110 (
b00111010000110100100101 )
b00111000011100000011011 *
b00111011010100100110010 +
0-
b011101 0
b011100 1
b11101 2
b011101 3
b1 4
b0000110100100101 6
b0011100000011011 7
b1010100100110010 8
b1010100100110010 9
b010000110100100101 :
b001001110000001101 ;
b011010100100110010 <
b011010100100110010 =
#840000000
0!
#850000000
1!
b10111011111010101101100 #
b00111001100110100100100 $
b10111010000111011011010 %
b10111010000111011011010 &
b101011 '
b10111011111010101101100 )
b00111001100110100100100 *
b10111010000111011011010 +
1,
1.
1/
b11101 2
b011101 3
b1111010101101100 6
b1100110100100100 7
b0000111011011010 8
b0000111011011010 9
b011111010101101100 :
b001110011010010010 ;
b010000111011011010 <
b010000111011011010 =
b0 >
#860000000
0!
#870000000
1!
b00111100001000001110100 #
b00111100001101000111100 $
b00111110001010101011000 %
b00111110001010101011000 &
b101100 '
b00111100001000001110100 )
b00111100001101000111100 *
b00111110001010101011000 +
0,
0.
0/
b011110 0
b011110 1
b11111 2
b011111 3
b0 4
b0001101000111100 6
b0001000001110100 7
b0001010101011000 8
b0001010101011000 9
b010001101000111100 :
b010001000001110100 ;
b100010101010110000 <
b010001010101011000 =
b11 >
#880000000
0!
#890000000
1!
b00111100101111000011010 #
b00110110001111001111111 $
b00111101000000111101001 %
b00111101000000111101001 &
b101101 '
b00111100101111000011010 )
b00110110001111001111111 *
b00111101000000111101001 +
b011011 1
b11110 2
b011110 3
b11 4
b0101111000011010 6
b0001111001111111 7
b1000000111101001 8
b1000000111101001 9
b010101111000011010 :
b000010001111001111 ;
b011000000111101001 <
b011000000111101001 =
b0 >
#900000000
0!
#910000000
1!
b10111010110110110111010 #
b10111100100011000000000 $
b10111101111110011011101 %
b10111101111110011011101 &
b101110 '
b10111010110110110111010 )
b10111100100011000000000 *
b10111101111110011011101 +
1,
1-
1.
1/
b011101 1
b1 4
b0100011000000000 6
b0110110110111010 7
b1111110011011101 8
b1111110011011101 9
b010100011000000000 :
b001011011011011101 ;
b011111110011011101 <
b011111110011011101 =
#920000000
0!
