float_adder.vhd
library IEEE;
use IEEE.std_logic_1164.all;
use IEEE.numeric_std.all;
use work.utils.all;

entity float_adder is
    generic (
        NE : natural := 8;
        NF : natural := 23);
    port (
        x_i : in std_logic_vector((NE + NF) downto 0);
        y_i : in std_logic_vector((NE + NF) downto 0);
        res_o : out std_logic_vector((NE + NF) downto 0)
    );
end float_adder;

architecture float_adder_arch of float_adder is

    --Bits de signo de cada uno de los registros
    signal sa : std_logic; --Bit signo del número mayor
    signal sb : std_logic; --Bit signo de número menor 
    signal sp : std_logic; --Bit signo parcial
    signal sr : std_logic; --Bit signo resultante
    signal sx : std_logic; --Bit signo de x_i
    signal sy : std_logic; --Bit signo de y_i

    --Bits de exponente de cada uno de los registros
    signal ea : unsigned(NE - 1 downto 0) := (others => '0'); --Exponente del número mayor
    signal eb : unsigned(NE - 1 downto 0) := (others => '0'); --Exponente del número menor
    signal ep : integer := 0; --Exponente parcial (tiene 1 bit más para verificar saturación) 
    signal er : unsigned(NE - 1 downto 0) := (others => '0'); --Exponente resultante si no  hay saturación
    signal edif: integer := 0; --Diferencia entre el exponente mayor y el menor
    signal esat : unsigned(NE - 1 downto 0) := (others => '0'); --Exponente resultante si hay saturación
    constant ezero : unsigned(NE - 1 downto 0) := (others => '0'); --Constante usada cuando resultado es cero
    signal ex : unsigned(NE - 1 downto 0); --Exponente de x_i
    signal ey : unsigned(NE - 1 downto 0); --Exponente de y_i

    --Bits de mantisa de cada uno de los registros
    signal ma : unsigned(NF - 1 downto 0) := (others => '0'); --Mantisa del número mayor
    signal mb : unsigned(NF - 1 downto 0) := (others => '0'); --Mantisa del número menor
    signal mp : unsigned(NF - 1 downto 0) := (others => '0'); --Mantisa resultante cuando no hay saturación
    constant msat : unsigned(NF - 1 downto 0) := (others => '1'); --Usada cuando hay saturación
    constant mzero : unsigned(NF - 1 downto 0) := (others => '0'); --Usada cuando resultado es cero
    signal mr : unsigned(NF - 1 downto 0) := (others => '0'); --Mantisa resultante
    signal mx : unsigned(NF - 1 downto 0); --Mantisa de cada una de x_i
    signal my : unsigned(NF - 1 downto 0); --Mantisa de cada una de y_i
 
    --Auxiliares
    signal aligna: unsigned(NF + (2**NE-2) + 1 downto 0) := (others => '0'); --Alineación del mayor (solo se concatena '1') 
    signal alignb: unsigned(NF + (2**NE-2) + 1 downto 0) := (others => '0'); --Alineación del menor
    signal sum: unsigned(NF + (2**NE-2) + 1 downto 0) := (others => '0'); --Resultado de la suma/resta (sin signo)
    signal sum_shifted: unsigned(NF + 1 downto 0) := (others => '0'); --Resultado de la suma/resta shifteada hasta primer '1'
    signal lead: integer := 0; --Cantidad de ceros que hay hasta el primer '1' de suma de mantisas alineadas

begin
    sx <= x_i(NF + NE);
    sy <= y_i(NF + NE);
    ex <= unsigned(x_i((NE + NF) - 1 downto NF));
    ey <= unsigned(y_i((NE + NF) - 1 downto NF));
    mx <= unsigned(x_i(NF - 1 downto 0));
    my <= unsigned(y_i(NF - 1 downto 0));

    --Inicialización exponente saturación
    esat(NE - 1 downto 1) <= (others => '1');
    esat(0) <= '0';

    --Se asigna el menor a "b" a y el mayor a "a":
    sa <= sx when ((ex & mx) > (ey & my)) else sy;
    ea <= ex when ((ex & mx) > (ey & my)) else ey;
    ma <= mx when ((ex & mx) > (ey & my)) else my;
    sb <= sy when ((ex & mx) > (ey & my)) else sx;
    eb <= ey when ((ex & mx) > (ey & my)) else ex;
    mb <= my when ((ex & mx) > (ey & my)) else mx;

    edif <= to_integer(ea - eb);
    --Se alinean los números:
    P_ALINACION: process(ma, mb, edif)
        variable auxa:  unsigned(NF + (2**NE-2) + 1 downto 0) := (others => '0');
        variable auxb:  unsigned(NF + (2**NE-2) + 1 downto 0) := (others => '0');
    begin
        auxa(NF + 1 downto 0) := "01" & ma; --Mantisa mayor alineada con 1 explícito
        auxa := auxa sll edif;
        auxb(NF + edif + 1 downto NF + 2) := (others => '0');
        auxb(NF + 1 downto 0) := "01" & mb; --Mantisa mayor alineada con 1 explícito

        aligna <= auxa;
        alignb <= auxb;
    end process;

    --Se realiza la suma/resta:
    sum <= (aligna + alignb) when (sa = sb) else (aligna - alignb);
    sp <= sa; --El signo del número resultante siempre va a ser igual al del mayor

    --Se obtiene el exponente y mantisas parciales:
    lead <= get_lead(sum(NF + edif downto 0));
    ep <= to_integer(ea) + 1 when sum(NF + edif + 1) = '1' and (sa = sb) else to_integer(ea) - lead;

    sum_shifted <= sum(NF + edif + 1 downto edif) when sum(NF + edif + 1 downto NF + edif) = "11" 
                    else sum(NF + edif + 1 downto edif) srl 1 when sum(NF + edif + 1 downto NF + edif) = "10" 
                    else sum(NF + edif + 1 downto edif) sll lead when (lead < NF);

    mp <= sum_shifted((NF - 1) downto 0); --Mantisa parcial, -1 en el rango para sacar el 1 implícito

    --Verificación de saturación y obtención de valores resultantes
    sr <= sp;
    er <= ezero when (ep < 0) else esat when (ep > to_integer(esat)) else to_unsigned(ep, NE);
    mr <= mzero when (ep < 0) else msat when (ep > to_integer(esat)) else mp;
     
    --Salida final
    res_o <= (std_logic_vector(sr & er & mr));

end float_adder_arch;

float_adder_tb.vhd
library IEEE;
use IEEE.std_logic_1164.all;
use IEEE.numeric_std.all;
use std.textio.all;

entity float_adder_tb is
end entity float_adder_tb;

architecture float_adder_tb_arch of float_adder_tb is

    constant FILE_PATH  : string := "test_sum_float_23_6.txt";
    constant TCK        : time := 20 ns; -- Periodo de reloj
    constant F_SIZE     : natural := 16; -- Tamaño de mantisa
    constant EXP_SIZE   : natural := 6;  -- Tamaño del exponente
    constant WORD_SIZE  : natural := EXP_SIZE + F_SIZE + 1; -- Tamaño de datos
   

    signal clk          : std_logic := '0';
    signal add_sub_tb   : std_logic := '0';
    signal x_file       : std_logic_vector(WORD_SIZE-1 downto 0) := (others => '0');
    signal y_file       : std_logic_vector(WORD_SIZE-1 downto 0) := (others => '0');
    signal z_file       : std_logic_vector(WORD_SIZE-1 downto 0) := (others => '0');
    signal z_dut        : std_logic_vector(WORD_SIZE-1 downto 0) := (others => '0');

    signal ciclos   : integer := 0;
    signal errores  : integer := 0;

    file datos : text open read_mode is FILE_PATH;
    
begin

    clk <= not(clk) after TCK/2; -- Reloj

    Test_Sequence: process 
        variable l   : line;
        variable ch  : character := ' ';
        variable aux : integer;
    begin
        while not(endfile(datos)) loop
            wait until rising_edge(clk);
            -- Solo para debugging
            ciclos <= ciclos + 1;
            -- Se lee una linea del archivo de valores de prueba
            readline(datos, l);
            -- Se extrae un entero de la linea
            read(l, aux);
            -- Se carga el valor del operando X
            x_file <= std_logic_vector(to_unsigned(aux, WORD_SIZE));
            -- Se lee un caracter (el espacio)
            read(l, ch);
            -- Se lee otro entero de la linea
            read(l, aux);
            -- Se carga el valor del operando Y
            y_file <= std_logic_vector(to_unsigned(aux, WORD_SIZE));
            -- Se lee otro caracter (el espacio)
            read(l, ch);
            -- Se lee otro entero
            read(l, aux);
            -- Se carga el valor de la salida (resultado)
            z_file <= std_logic_vector(to_unsigned(aux, WORD_SIZE));
        end loop;
    
        file_close(datos); -- Se cierra el archivo

        
        -- Se aborta la simulacion (fin del archivo)
        assert false report
            "Fin de la simulacion" severity failure;

    end process Test_Sequence;

    -- Instanciacion del DUT
    DUT: entity work.float_adder
    generic map(
        NF => F_SIZE,
        NE => EXP_SIZE
    )
    port map(
        x_i       => x_file,
        y_i       => y_file,
        res_o       => z_dut
    );


    verificacion: process(clk)
    begin
        if rising_edge(clk) then
            assert to_integer(unsigned(z_file)) = to_integer(unsigned(z_dut)) report
                "Error: Salida del DUT no coincide con referencia (salida del DUT = " &
                integer'image(to_integer(unsigned(z_dut))) &
                ", salida del archivo = " &
                integer'image(to_integer(unsigned(z_file))) & ")"
                severity warning;
            
            if to_integer(unsigned(z_file)) /= to_integer(unsigned(z_dut)) then
                errores <= errores + 1;
            end if;
        end if;
    end process;

end architecture float_adder_tb_arch;

float_adder_tb.vcd
$date
  Mon Nov 20 12:54:59 2023
$end
$version
  GHDL v0
$end
$timescale
  1 fs
$end
$scope module standard $end
$upscope $end
$scope module std_logic_1164 $end
$upscope $end
$scope module numeric_std $end
$upscope $end
$scope module textio $end
$upscope $end
$scope module utils $end
$upscope $end
$scope module float_adder_tb $end
$var reg 1 ! clk $end
$var reg 1 " add_sub_tb $end
$var reg 23 # x_file[22:0] $end
$var reg 23 $ y_file[22:0] $end
$var reg 23 % z_file[22:0] $end
$var reg 23 & z_dut[22:0] $end
$var integer 32 ' ciclos $end
$var integer 32 ( errores $end
$scope module dut $end
$var reg 23 ) x_i[22:0] $end
$var reg 23 * y_i[22:0] $end
$var reg 23 + res_o[22:0] $end
$var reg 1 , sa $end
$var reg 1 - sb $end
$var reg 1 . sp $end
$var reg 1 / sr $end
$var reg 1 0 sx $end
$var reg 1 1 sy $end
$var reg 6 2 ea[5:0] $end
$var reg 6 3 eb[5:0] $end
$var integer 32 4 ep $end
$var reg 6 5 er[5:0] $end
$var integer 32 6 edif $end
$var reg 6 7 esat[5:0] $end
$var reg 6 8 ex[5:0] $end
$var reg 6 9 ey[5:0] $end
$var reg 16 : ma[15:0] $end
$var reg 16 ; mb[15:0] $end
$var reg 16 < mp[15:0] $end
$var reg 16 = mr[15:0] $end
$var reg 16 > mx[15:0] $end
$var reg 16 ? my[15:0] $end
$var reg 80 @ aligna[79:0] $end
$var reg 80 A alignb[79:0] $end
$var reg 80 B sum[79:0] $end
$var reg 18 C sum_shifted[17:0] $end
$var integer 32 D lead $end
$upscope $end
$upscope $end
$enddefinitions $end
#0
0!
0"
b00000000000000000000000 #
b00000000000000000000000 $
b00000000000000000000000 %
b00000010000000000000000 &
b0 '
b0 (
b00000000000000000000000 )
b00000000000000000000000 *
b00000010000000000000000 +
0,
0-
0.
0/
00
01
b000000 2
b000000 3
b1 4
b000001 5
b0 6
b111110 7
b000000 8
b000000 9
b0000000000000000 :
b0000000000000000 ;
b0000000000000000 <
b0000000000000000 =
b0000000000000000 >
b0000000000000000 ?
b00000000000000000000000000000000000000000000000000000000000000010000000000000000 @
b00000000000000000000000000000000000000000000000000000000000000010000000000000000 A
b00000000000000000000000000000000000000000000000000000000000000100000000000000000 B
b010000000000000000 C
b10000 D
#10000000
1!
b10110111100110100100100 #
b10111100001000000001001 $
b10111100100100110101101 %
b10111100100100110101101 &
b1 '
b1 (
b10110111100110100100100 )
b10111100001000000001001 *
b10111100100100110101101 +
1,
1-
1.
1/
10
11
b011110 2
b011011 3
b11110 4
b011110 5
b11 6
b011011 8
b011110 9
b0001000000001001 :
b1100110100100100 ;
b0100100110101101 <
b0100100110101101 =
b1100110100100100 >
b0001000000001001 ?
b00000000000000000000000000000000000000000000000000000000000010001000000001001000 @
b00000000000000000000000000000000000000000000000000000000000000011100110100100100 A
b00000000000000000000000000000000000000000000000000000000000010100100110101101100 B
b010100100110101101 C
b0 D
#20000000
0!
#30000000
1!
b10111100011001001100111 #
b10111001101100011011011 $
b10111101010100010011101 %
b10111101010100010011101 &
b10 '
b10111100011001001100111 )
b10111001101100011011011 *
b10111101010100010011101 +
b011100 3
b11110 4
b011110 5
b10 6
b011110 8
b011100 9
b0011001001100111 :
b1101100011011011 ;
b1010100010011101 <
b1010100010011101 =
b0011001001100111 >
b1101100011011011 ?
b00000000000000000000000000000000000000000000000000000001001001001100100110011100 @
b00000000000000000000000000000000000000000000000000000000000000011101100011011011 A
b00000000000000000000000000000000000000000000000000000001001001101010001001110111 B
b011010100010011101 C
b0 D
#40000000
0!
#50000000
1!
b00111000011110110110111 #
b00111100101000111111000 $
b00111101010000101100101 %
b00111101010000101100101 &
b11 '
b00111000011110110110111 )
b00111100101000111111000 *
b00111101010000101100101 +
0,
0-
0.
0/
00
01
b011100 8
b011110 9
b0101000111111000 :
b0011110110110111 ;
b1010000101100101 <
b1010000101100101 =
b0011110110110111 >
b0101000111111000 ?
b00000000000000000000000000000000000000000000000000000100100101010100011111100000 @
b00000000000000000000000000000000000000000000000000000000000000010011110110110111 A
b00000000000000000000000000000000000000000000000000000100100101101000010110010111 B
b011010000101100101 C
#60000000
0!
#70000000
1!
b00111001100011001111011 #
b10111010100010110010001 $
b10110111000100101001110 %
b10110111000100101001100 &
b100 '
b00111001100011001111011 )
b10111010100010110010001 *
b10110111000100101001100 +
1,
1.
1/
11
b011101 2
b11011 4
b011011 5
b1 6
b011101 9
b0100010110010001 :
b1100011001111011 ;
b1000100101001100 <
b1000100101001100 =
b1100011001111011 >
b0100010110010001 ?
b00000000000000000000000000000000000000000000000000100100101010101000101100100010 @
b00000000000000000000000000000000000000000000000000000000000000011100011001111011 A
b00000000000000000000000000000000000000000000000000100100101010001100010010100111 B
b011000100101001100 C
b10 D
#80000000
0!
#90000000
1!
b10110110111110000111100 #
b10110111100101000111001 $
b10111001010001100111010 %
b10111000100011001110101 &
b101 '
b10 (
b10110110111110000111100 )
b10110111100101000111001 *
b10111000100011001110101 +
1-
10
b011011 2
b011011 3
b11100 4
b011100 5
b0 6
b011011 8
b011011 9
b1100101000111001 :
b0111110000111100 ;
b0100011001110101 <
b0100011001110101 =
b0111110000111100 >
b1100101000111001 ?
b00000000000000000000000000000000000000000000000001001001010100011100101000111001 @
b00000000000000000000000000000000000000000000000000000000000000010111110000111100 A
b00000000000000000000000000000000000000000000000001001001010100110100011001110101 B
b110100011001110101 C
b0 D
#100000000
0!
#110000000
1!
b10111000111110000001100 #
b10111011010010100010100 $
b10111100011000110001101 %
b10111100011000110001101 &
b110 '
b11 (
b10111000111110000001100 )
b10111011010010100010100 *
b10111100011000110001101 +
b011101 2
b011100 3
b11110 4
b011110 5
b1 6
b011100 8
b011101 9
b1010010100010100 :
b0111110000001100 ;
b0011000110001101 <
b0011000110001101 =
b0111110000001100 >
b1010010100010100 ?
b00000000000000000000000000000000000000000000000010010010101000110100101000101000 @
b00000000000000000000000000000000000000000000000000000000000000010111110000001100 A
b00000000000000000000000000000000000000000000000010010010101001001100011000110100 B
b010011000110001101 C
b10 D
#120000000
0!
#130000000
1!
b10111011000110100111101 #
b00110000110011101100100 $
b10111011000001000000001 %
b10111011000001000000001 &
b111 '
b10111011000110100111101 )
b00110000110011101100100 *
b10111011000001000000001 +
0-
01
b011000 3
b11101 4
b011101 5
b101 6
b011101 8
b011000 9
b1000110100111101 :
b0110011101100100 ;
b1000001000000001 <
b1000001000000001 =
b1000110100111101 >
b0110011101100100 ?
b00000000000000000000000000000000000000000010010010101000001100011010011110100000 @
b00000000000000000000000000000000000000000000000000000000000000010110011101100100 A
b00000000000000000000000000000000000000000010010010101000001100000100000000111100 B
b011000001000000001 C
b0 D
#140000000
0!
#150000000
1!
b00111101110100011100000 #
b00110111101001001101100 $
b00111110001000110010110 %
b00111110001000110010110 &
b1000 '
b00111101110100011100000 )
b00110111101001001101100 *
b00111110001000110010110 +
0,
0.
0/
00
b011110 2
b011011 3
b11111 4
b011111 5
b11 6
b011110 8
b011011 9
b1110100011100000 :
b1101001001101100 ;
b0001000110010110 <
b0001000110010110 =
b1110100011100000 >
b1101001001101100 ?
b00000000000000000000000000000000001001001010100000110001111011110100011100000000 @
b00000000000000000000000000000000000000000000000000000000000000011101001001101100 A
b00000000000000000000000000000000001001001010100000110001111100010001100101101100 B
b010001000110010110 C
b11 D
#160000000
0!
#170000000
1!
b00111100000010010001101 #
b00111010100001011110001 $
b00111101010011000000101 %
b00111101010011000000101 &
b1001 '
b00111100000010010001101 )
b00111010100001011110001 *
b00111101010011000000101 +
b011101 3
b11110 4
b011110 5
b1 6
b011101 9
b0000010010001101 :
b0100001011110001 ;
b1010011000000101 <
b1010011000000101 =
b0000010010001101 >
b0100001011110001 ?
b00000000000000000000000000000010010010101000001100011110110100100000100100011010 @
b00000000000000000000000000000000000000000000000000000000000000010100001011110001 A
b00000000000000000000000000000010010010101000001100011110110100110100110000001011 B
b011010011000000101 C
b0 D
#180000000
0!
#190000000
1!
b00110011110111101001011 #
b00111001010100001111010 $
b00111001110011001100011 %
b00111001110011001100011 &
b1010 '
b00110011110111101001011 )
b00111001010100001111010 *
b00111001110011001100011 +
b011100 2
b011001 3
b11100 4
b011100 5
b11 6
b011001 8
b011100 9
b1010100001111010 :
b1110111101001011 ;
b1110011001100011 <
b1110011001100011 =
b1110111101001011 >
b1010100001111010 ?
b00000000000000000000000000100100101010000011000111101101000011010100001111010000 @
b00000000000000000000000000000000000000000000000000000000000000011110111101001011 A
b00000000000000000000000000100100101010000011000111101101000011110011001100011011 B
b011110011001100011 C
b0 D
#200000000
0!
#210000000
1!
b10101110100000010100000 #
b00111011010010000011000 $
b00111011001111100010101 %
b00111011001111100010101 &
b1011 '
b10101110100000010100000 )
b00111011010010000011000 *
b00111011001111100010101 +
1-
10
b011101 2
b010111 3
b11101 4
b011101 5
b110 6
b010111 8
b011101 9
b1010010000011000 :
b0100000010100000 ;
b1001111100010101 <
b1001111100010101 =
b0100000010100000 >
b1010010000011000 ?
b00000000000000000100100101010000011000111101101000011011011010010000011000000000 @
b00000000000000000000000000000000000000000000000000000000000000010100000010100000 A
b00000000000000000100100101010000011000111101101000011011011001111100010101100000 B
b011001111100010101 C
b0 D
#220000000
0!
#230000000
1!
b10111011010110111011100 #
b00111011011100000100100 $
b00110000100100100000000 %
b00110000100100100000000 &
b1100 '
b10111011010110111011100 )
b00111011011100000100100 *
b00110000100100100000000 +
b011101 3
b11000 4
b011000 5
b0 6
b011101 8
b1011100000100100 :
b1010110111011100 ;
b0100100100000000 <
b0100100100000000 =
b1010110111011100 >
b1011100000100100 ?
b00000000000100100101010000011000111101101000011011011010011011011011100000100100 @
b00000000000000000000000000000000000000000000000000000000000000011010110111011100 A
b00000000000100100101010000011000111101101000011011011010011011000000101001001000 B
b010100100100000000 C
b101 D
#240000000
0!
#250000000
1!
b10111000100100110000010 #
b00111001111000001011110 $
b00110110100110110111000 %
b00110110100110110111000 &
b1101 '
b10111000100100110000010 )
b00111001111000001011110 *
b00110110100110110111000 +
b011100 2
b011100 3
b11011 4
b011011 5
b011100 8
b011100 9
b1111000001011110 :
b0100100110000010 ;
b0100110110111000 <
b0100110110111000 =
b0100100110000010 >
b1111000001011110 ?
b00000000000100100101010000011000111101101000011011011010011011011111000001011110 @
b00000000000000000000000000000000000000000000000000000000000000010100100110000010 A
b00000000000100100101010000011000111101101000011011011010011011001010011011011100 B
b010100110110111000 C
b1 D
#260000000
0!
#270000000
1!
b10111010011110100101110 #
b00110011110111101001111 $
b10111010001111000111001 %
b10111010001111000111001 &
b1110 '
b10111010011110100101110 )
b00110011110111101001111 *
b10111010001111000111001 +
1,
0-
1.
1/
b011101 2
b011001 3
b11101 4
b011101 5
b100 6
b011101 8
b011001 9
b0011110100101110 :
b1110111101001111 ;
b0001111000111001 <
b0001111000111001 =
b0011110100101110 >
b1110111101001111 ?
b00000001001001010100000110001111011010000110110110100110110100111101001011100000 @
b00000000000000000000000000000000000000000000000000000000000000011110111101001111 A
b00000001001001010100000110001111011010000110110110100110110100011110001110010001 B
b010001111000111001 C
b0 D
#280000000
0!
#290000000
1!
b10111011010111101101010 #
b00111001001000000101010 $
b10111001100111010101010 %
b10111001100111010101010 &
b1111 '
b10111011010111101101010 )
b00111001001000000101010 *
b10111001100111010101010 +
b011100 3
b11100 4
b011100 5
b1 6
b011100 9
b1010111101101010 :
b1001000000101010 ;
b1100111010101010 <
b1100111010101010 =
b1010111101101010 >
b1001000000101010 ?
b00100100101010000011000111101101000011011011010011011010001100110101111011010100 @
b00000000000000000000000000000000000000000000000000000000000000011001000000101010 A
b00100100101010000011000111101101000011011011010011011010001100011100111010101010 B
b011100111010101010 C
b1 D
#300000000
0!
#310000000
1!
b00111001110110100100011 #
b10111001100010111111011 $
b00110010011100101000000 %
b00110010011100101000000 &
b10000 '
b00111001110110100100011 )
b10111001100010111111011 *
b00110010011100101000000 +
0,
1-
0.
0/
00
11
b011100 2
b11001 4
b011001 5
b0 6
b011100 8
b1110110100100011 :
b1100010111111011 ;
b0011100101000000 <
b0011100101000000 =
b1110110100100011 >
b1100010111111011 ?
b01001001010100000110001111011010000110110110100110110100011000011110110100100011 @
b00000000000000000000000000000000000000000000000000000000000000011100010111111011 A
b01001001010100000110001111011010000110110110100110110100011000000010011100101000 B
b010011100101000000 C
b11 D
#320000000
0!
#330000000
1!
b00111001011100111011101 #
b10111010101100100010111 $
b10110111111000010100010 %
b10110111111000010100000 &
b10001 '
b00111001011100111011101 )
b10111010101100100010111 *
b10110111111000010100000 +
1,
0-
1.
1/
b011101 2
b11011 4
b011011 5
b1 6
b011101 9
b0101100100010111 :
b1011100111011101 ;
b1111000010100000 <
b1111000010100000 =
b1011100111011101 >
b0101100100010111 ?
b10010010101000001100011110110100001101101101001101101000110000101011001000101110 @
b00000000000000000000000000000000000000000000000000000000000000011011100111011101 A
b10010010101000001100011110110100001101101101001101101000110000001111100001010001 B
b011111000010100000 C
b10 D
#340000000
0!
#350000000
1!
b10110110111111101010100 #
b00111001101000111000010 $
b00111000001001000011000 %
b00111000001001000011000 &
b10010 '
b100 (
b10110110111111101010100 )
b00111001101000111000010 *
b00111000001001000011000 +
0,
1-
0.
0/
10
01
b011100 2
b011011 3
b11100 4
b011100 5
b011011 8
b011100 9
b1101000111000010 :
b0111111101010100 ;
b0001001000011000 <
b0001001000011000 =
b0111111101010100 >
b1101000111000010 ?
b00100101010000011000111101101000011011011010011011010001100000111010001110000100 @
b00000000000000000000000000000000000000000000000000000000000000010111111101010100 A
b00100101010000011000111101101000011011011010011011010001100000100010010000110000 B
b010001001000011000 C
b0 D
#360000000
0!
#370000000
1!
b10111000101001110110100 #
b00111011001110110001010 $
b00111001110011101100000 %
b00111001110011101100000 &
b10011 '
b10111000101001110110100 )
b00111011001110110001010 *
b00111001110011101100000 +
b011101 2
b011100 3
b11100 4
b011100 5
b011100 8
b011101 9
b1001110110001010 :
b0101001110110100 ;
b1110011101100000 <
b1110011101100000 =
b0101001110110100 >
b1001110110001010 ?
b01001010100000110001111011010000110110110100110110100011000000110011101100010100 @
b00000000000000000000000000000000000000000000000000000000000000010101001110110100 A
b01001010100000110001111011010000110110110100110110100011000000011110011101100000 B
b011110011101100000 C
b1 D
#380000000
0!
#390000000
1!
b10111000001000001010000 #
b00111010100010001101101 $
b00111000111100010001010 %
b00111000111100010001010 &
b10100 '
b10111000001000001010000 )
b00111010100010001101101 *
b00111000111100010001010 +
b0100010001101101 :
b0001000001010000 ;
b0111100010001010 <
b0111100010001010 =
b0001000001010000 >
b0100010001101101 ?
b10010101000001100011110110100001101101101001101101000110000000101000100011011010 @
b00000000000000000000000000000000000000000000000000000000000000010001000001010000 A
b10010101000001100011110110100001101101101001101101000110000000010111100010001010 B
b010111100010001010 C
#400000000
0!
#410000000
1!
b10111001010010110010001 #
b00110100000110100110001 $
b10111000110001001000100 %
b10111000110001001000100 &
b10101 '
b10111001010010110010001 )
b00110100000110100110001 *
b10111000110001001000100 +
1,
0-
1.
1/
b011100 2
b011010 3
b11100 4
b011100 5
b10 6
b011010 9
b1010010110010001 :
b0000110100110001 ;
b0110001001000100 <
b0110001001000100 =
b1010010110010001 >
b0000110100110001 ?
b10101000001100011110110100001101101101001101101000110000000001101001011001000100 @
b00000000000000000000000000000000000000000000000000000000000000010000110100110001 A
b10101000001100011110110100001101101101001101101000110000000001011000100100010011 B
b010110001001000100 C
b0 D
#420000000
0!
#430000000
1!
b00110110001000101010000 #
b10111011011101101111111 $
b10111010111011100101011 %
b10111010111011100101011 &
b10110 '
b00110110001000101010000 )
b10111011011101101111111 *
b10111010111011100101011 +
00
11
b011101 2
b011011 3
b11101 4
b011101 5
b011011 8
b011101 9
b1011101101111111 :
b0001000101010000 ;
b0111011100101011 <
b0111011100101011 =
b0001000101010000 >
b1011101101111111 ?
b10100000110001111011010000110110110100110110100011000000000101101110110111111100 @
b00000000000000000000000000000000000000000000000000000000000000010001000101010000 A
b10100000110001111011010000110110110100110110100011000000000101011101110010101100 B
b010111011100101011 C
#440000000
0!
#450000000
1!
b00111010010110001101100 #
b00110100101100111111110 $
b00111010101011110101011 %
b00111010101011110101011 &
b10111 '
b00111010010110001101100 )
b00110100101100111111110 *
b00111010101011110101011 +
0,
0.
0/
01
b011010 3
b11101 4
b011101 5
b11 6
b011101 8
b011010 9
b0010110001101100 :
b0101100111111110 ;
b0101011110101011 <
b0101011110101011 =
b0010110001101100 >
b0101100111111110 ?
b00011000111101101000011011011010011011010001100000000010101010010110001101100000 @
b00000000000000000000000000000000000000000000000000000000000000010101100111111110 A
b00011000111101101000011011011010011011010001100000000010101010101011110101011110 B
b010101011110101011 C
b0 D
#460000000
0!
#470000000
1!
b10110101010000011010111 #
b00111000101000100010101 $
b00110111101000110111110 %
b00110111101000110111110 &
b11000 '
b10110101010000011010111 )
b00111000101000100010101 *
b00110111101000110111110 +
1-
10
b011100 2
b11011 4
b011011 5
b10 6
b011010 8
b011100 9
b0101000100010101 :
b1010000011010111 ;
b1101000110111110 <
b1101000110111110 =
b1010000011010111 >
b0101000100010101 ?
b00011110110100001101101101001101101000110000000001010101001001010100010001010100 @
b00000000000000000000000000000000000000000000000000000000000000011010000011010111 A
b00011110110100001101101101001101101000110000000001010101001000111010001101111101 B
b011101000110111110 C
b1 D
#480000000
0!
#490000000
1!
b00110110000111101101111 #
b10111000110101001010111 $
b10110111100010100111111 %
b10110111100010100111110 &
b11001 '
b00110110000111101101111 )
b10111000110101001010111 *
b10110111100010100111110 +
1,
0-
1.
1/
00
11
b011011 3
b11011 4
b011011 5
b1 6
b011011 8
b0110101001010111 :
b0000111101101111 ;
b1100010100111110 <
b1100010100111110 =
b0000111101101111 >
b0110101001010111 ?
b11110110100001101101101001101101000110000000001010101001001010101101010010101110 @
b00000000000000000000000000000000000000000000000000000000000000010000111101101111 A
b11110110100001101101101001101101000110000000001010101001001010011100010100111111 B
b011100010100111110 C
b1 D
#500000000
0!
#510000000
1!
b10110110100010101111100 #
b00111011011110111110101 $
b00111010110110010010110 %
b00111010110110010010110 &
b11010 '
b101 (
b10110110100010101111100 )
b00111011011110111110101 *
b00111010110110010010110 +
0,
1-
0.
0/
10
01
b011101 2
b11101 4
b011101 5
b10 6
b011101 9
b1011110111110101 :
b0100010101111100 ;
b0110110010010110 <
b0110110010010110 =
b0100010101111100 >
b1011110111110101 ?
b10110100001101101101001101101000110000000001010101001001010001101111011111010100 @
b00000000000000000000000000000000000000000000000000000000000000010100010101111100 A
b10110100001101101101001101101000110000000001010101001001010001011011001001011000 B
b010110110010010110 C
b0 D
#520000000
0!
#530000000
1!
b00110100001010011100101 #
b10111100000110001011010 $
b10111011111011000010111 %
b10111011111011000010110 &
b11011 '
b00110100001010011100101 )
b10111100000110001011010 *
b10111011111011000010110 +
1,
0-
1.
1/
00
11
b011110 2
b011010 3
b11101 4
b011101 5
b100 6
b011010 8
b011110 9
b0000110001011010 :
b0001010011100101 ;
b1111011000010110 <
b1111011000010110 =
b0001010011100101 >
b0000110001011010 ?
b00001101101101001101101000110000000001010101001001010001010100001100010110100000 @
b00000000000000000000000000000000000000000000000000000000000000010001010011100101 A
b00001101101101001101101000110000000001010101001001010001010011111011000010111011 B
b011111011000010110 C
b1 D
#540000000
0!
#550000000
1!
b10110011101010011010100 #
b10110101011111011011010 $
b10110110101010010100010 %
b10110110101010010100010 &
b11100 '
b110 (
b10110011101010011010100 )
b10110101011111011011010 *
b10110110101010010100010 +
1-
10
b011010 2
b011001 3
b11011 4
b011011 5
b1 6
b011001 8
b011010 9
b1011111011011010 :
b1101010011010100 ;
b0101010010100010 <
b0101010010100010 =
b1101010011010100 >
b1011111011011010 ?
b10110110100110110100011000000000101010100100101000101010001100110111110110110100 @
b00000000000000000000000000000000000000000000000000000000000000011101010011010100 A
b10110110100110110100011000000000101010100100101000101010001101010101001010001000 B
b010101010010100010 C
#560000000
0!
#570000000
1!
b00111011110110001001100 #
b10111001111010010100011 $
b00111001110001111110101 %
b00111001110001111110100 &
b11101 '
b00111011110110001001100 )
b10111001111010010100011 *
b00111001110001111110100 +
0,
0.
0/
00
b011101 2
b011100 3
b11100 4
b011100 5
b011101 8
b011100 9
b1110110001001100 :
b1111010010100011 ;
b1110001111110100 <
b1110001111110100 =
b1110110001001100 >
b1111010010100011 ?
b01101101001101101000110000000001010101001001010001010100011000111101100010011000 @
b00000000000000000000000000000000000000000000000000000000000000011111010010100011 A
b01101101001101101000110000000001010101001001010001010100011000011110001111110101 B
b011110001111110100 C
#580000000
0!
#590000000
1!
b10110110101011100101010 #
b00110110100101100000001 $
b10101101000010100100000 %
b10101101000010100100000 &
b11110 '
b111 (
b10110110101011100101010 )
b00110110100101100000001 *
b10101101000010100100000 +
1,
0-
1.
1/
10
01
b011011 2
b011011 3
b10110 4
b010110 5
b0 6
b011011 8
b011011 9
b0101011100101010 :
b0100101100000001 ;
b1000010100100000 <
b1000010100100000 =
b0101011100101010 >
b0100101100000001 ?
b11011010011011010001100000000010101010010010100010101000110000010101011100101010 @
b00000000000000000000000000000000000000000000000000000000000000010100101100000001 A
b11011010011011010001100000000010101010010010100010101000110000000000110000101001 B
b011000010100100000 C
b101 D
#600000000
0!
#610000000
1!
b10110010011100011001011 #
b10111110010011000100001 $
b10111110010101100000100 %
b10111110010101100000100 &
b11111 '
b10110010011100011001011 )
b10111110010011000100001 *
b10111110010101100000100 +
1-
11
b011111 2
b011001 3
b11111 4
b011111 5
b110 6
b011001 8
b011111 9
b0010011000100001 :
b0011100011001011 ;
b0010101100000100 <
b0010101100000100 =
b0011100011001011 >
b0010011000100001 ?
b10011011010001100000000010101010010010100010101000110000010010011000100001000000 @
b00000000000000000000000000000000000000000000000000000000000000010011100011001011 A
b10011011010001100000000010101010010010100010101000110000010010101100000100001011 B
b010010101100000100 C
b0 D
#620000000
0!
